calciumcurator/__init__.py
calciumcurator/__main__.py
calciumcurator/_version.py
calciumcurator/calcium_curator.py
calciumcurator/contour_manager.py
calciumcurator/view_cli.py
calciumcurator/extensions/__init__.py
calciumcurator/extensions/cell_mask.py
calciumcurator/extensions/lineplot.py
calciumcurator/extensions/threshold.py
calciumcurator/images/__init__.py
calciumcurator/images/masks.py
calciumcurator/io/__init__.py
calciumcurator/io/caiman/__init__.py
calciumcurator/io/caiman/_vendored.py
calciumcurator/io/caiman/caiman_reader.py
calciumcurator/io/s2p/__init__.py
calciumcurator/io/s2p/s2p_reader.py
calciumcurator/io/utils/__init__.py
calciumcurator/io/utils/data_range.py
calciumcurator/qt/__init__.py
calciumcurator/qt/dock_widgets.py
calciumcurator/qt/mode_controls.py
calciumcurator/qt/plots.py
calciumcurator-0.0.8.dist-info/LICENSE
calciumcurator-0.0.8.dist-info/METADATA
calciumcurator-0.0.8.dist-info/WHEEL
calciumcurator-0.0.8.dist-info/entry_points.txt
calciumcurator-0.0.8.dist-info/top_level.txt
calciumcurator-0.0.8.dist-info/RECORD
