Metadata-Version: 2.1
Name: calciumcurator
Version: 0.0.8
Summary: a GUI for curating and exploring calcium imaging data
Home-page: https://github.com/donatolab/calciumcurator
Author: Donato Lab
License: BSD 3-Clause
Download-URL: https://github.com/donatolab/calciumcurator
Platform: UNKNOWN
Classifier: Development Status :: 3 - Alpha
Classifier: Environment :: X11 Applications :: Qt
Classifier: Intended Audience :: Education
Classifier: Intended Audience :: Science/Research
Classifier: License :: OSI Approved :: GNU General Public License v3 (GPLv3)
Classifier: Programming Language :: C
Classifier: Programming Language :: Python
Classifier: Programming Language :: Python :: 3 :: Only
Classifier: Programming Language :: Python :: 3.6
Classifier: Programming Language :: Python :: 3.7
Classifier: Programming Language :: Python :: 3.8
Classifier: Topic :: Scientific/Engineering
Classifier: Topic :: Scientific/Engineering :: Visualization
Classifier: Topic :: Scientific/Engineering :: Information Analysis
Classifier: Topic :: Scientific/Engineering :: Bio-Informatics
Classifier: Topic :: Utilities
Classifier: Operating System :: Microsoft :: Windows
Classifier: Operating System :: POSIX
Classifier: Operating System :: Unix
Classifier: Operating System :: MacOS
Requires-Python: >=3.6
Requires-Dist: h5py
Requires-Dist: napari[all]
Requires-Dist: numpy
Requires-Dist: pyqtgraph
Requires-Dist: scikit-image
